imgdedup.py
dedup_image-1.0.0.dist-info/METADATA
dedup_image-1.0.0.dist-info/WHEEL
dedup_image-1.0.0.dist-info/entry_points.txt
dedup_image-1.0.0.dist-info/top_level.txt
dedup_image-1.0.0.dist-info/RECORD
