Metadata-Version: 2.4
Name: dedup-image
Version: 1.0.0
Summary: A fast, offline CLI tool to find and remove visually duplicate images.
Home-page: https://github.com/Shailesh7860/dedup-image
Author: Shailesh Suvarna
Author-email: shaileshsuvarna24@gmail.com
Classifier: Programming Language :: Python :: 3
Classifier: Programming Language :: Python :: 3.7
Classifier: Programming Language :: Python :: 3.8
Classifier: Programming Language :: Python :: 3.9
Classifier: Programming Language :: Python :: 3.10
Classifier: Programming Language :: Python :: 3.11
Classifier: License :: OSI Approved :: MIT License
Classifier: Operating System :: OS Independent
Classifier: Topic :: Multimedia :: Graphics
Classifier: Development Status :: 4 - Beta
Requires-Python: >=3.7
Requires-Dist: imutils
Requires-Dist: numpy
Requires-Dist: opencv-python
Dynamic: author
Dynamic: author-email
Dynamic: classifier
Dynamic: description
Dynamic: description-content-type
Dynamic: home-page
Dynamic: requires-dist
Dynamic: requires-python
Dynamic: summary
